dockerfile_assistant/__init__.py
dockerfile_assistant/agent.py
dockerfile_assistant/config.py
dockerfile_assistant/mcp_fs.py
dockerfile_assistant/model.py
dockerfile_assistant/run_cli.py
dockerfile_assistant/system_prompt.py
dockerfile_assistant/prompts/default_prompt.md
dockerfile_assistant/prompts/fs_mcp_prompt.md
dockerfile_assistant-1.0.0.dist-info/licenses/LICENSE
dockerfile_assistant-1.0.0.dist-info/METADATA
dockerfile_assistant-1.0.0.dist-info/WHEEL
dockerfile_assistant-1.0.0.dist-info/entry_points.txt
dockerfile_assistant-1.0.0.dist-info/top_level.txt
dockerfile_assistant-1.0.0.dist-info/RECORD
