Metadata-Version: 2.4
Name: dockerfile-assistant
Version: 1.0.0
Summary: AI-powered Dockerfile generation and analysis
Author-email: Giuliano Testa <giulianotesta15@gmail.com>
License-Expression: MIT
Project-URL: Homepage, https://github.com/giulianotesta7/dockerfile-assistant
Project-URL: Repository, https://github.com/giulianotesta7/dockerfile-assistant
Project-URL: Issues, https://github.com/giulianotesta7/dockerfile-assistant/issues
Keywords: dockerfile,docker,ai,assistant,pydantic-ai
Requires-Python: >=3.10
License-File: LICENSE
Requires-Dist: pydantic-ai>=1.37.0
Requires-Dist: python-dotenv>=1.0.0
Provides-Extra: dev
Requires-Dist: pytest>=7.0.0; extra == "dev"
Requires-Dist: black; extra == "dev"
Requires-Dist: ruff; extra == "dev"
Dynamic: license-file
